Metadata-Version: 1.1
Name: AmpliPython
Version: 1.2.1
Summary: AmpliPython is lightweight Amplitude Integration for event logging
Home-page: https://github.com/Alveona/AmpliPython
Author: Alveona
Author-email: pomavau@yandex.ru
License: MIT
Platform: any
Classifier: Development Status :: 4 - Beta
Classifier: Environment :: Web Environment
Classifier: Intended Audience :: Developers
Classifier: License :: OSI Approved :: MIT License
Classifier: Operating System :: OS Independent
Classifier: Programming Language :: Python
Classifier: Topic :: Internet :: WWW/HTTP :: Dynamic Content
Classifier: Topic :: Software Development :: Libraries :: Python Modules
